tonic_reporting/__init__.py
tonic_reporting/ml_utility.py
tonic_reporting/multivariate.py
tonic_reporting/privacy.py
tonic_reporting/reporting.py
tonic_reporting/styling.py
tonic_reporting/univariate.py
tonic_reporting/util.py
tonic_reporting-1.5.0.dist-info/LICENSE
tonic_reporting-1.5.0.dist-info/WHEEL
tonic_reporting-1.5.0.dist-info/METADATA
tonic_reporting-1.5.0.dist-info/RECORD
