Metadata-Version: 2.1
Name: tonic-reporting
Version: 1.5.0
Summary: Tools for evaluating fidelity and privacy of synthetic data
Home-page: https://www.tonic.ai/
License: MIT
Keywords: tonic.ai,tonic
Author: Eric Timmerman
Author-email: eric@tonic.ai
Requires-Python: >=3.8
Classifier: License :: OSI Approved :: MIT License
Classifier: Operating System :: OS Independent
Classifier: Programming Language :: Python :: 3
Classifier: Programming Language :: Python :: 3.8
Classifier: Programming Language :: Python :: 3.9
Classifier: Programming Language :: Python :: 3.10
Classifier: Programming Language :: Python :: 3.11
Requires-Dist: matplotlib (>=3.0.0,<4.0.0)
Requires-Dist: numpy (>=1.0.0,<2.0.0)
Requires-Dist: pandas (>=1.0.0,<2.0.0)
Requires-Dist: scikit-learn (>=1.1.0,<2.0.0)
Requires-Dist: scipy (>=1.7.3,<2.0.0)
